README.md
ez_setup.py
setup.py
dispatch/__init__.py
dispatch/dispatcher.py
dispatch/saferef.py
django_dispatch.egg-info/PKG-INFO
django_dispatch.egg-info/SOURCES.txt
django_dispatch.egg-info/dependency_links.txt
django_dispatch.egg-info/requires.txt
django_dispatch.egg-info/top_level.txt
tests/__init__.py
tests/test_dispatcher.py
tests/test_saferef.py